cover_crypt-14.0.0.dist-info/METADATA
cover_crypt-14.0.0.dist-info/WHEEL
cover_crypt-14.0.0.dist-info/license_files/LICENSE.md
cloudproof_cover_crypt/__init__.py
cloudproof_cover_crypt/__init__.pyi
cloudproof_cover_crypt/py.typed
cloudproof_cover_crypt/cloudproof_cover_crypt.abi3.so
cover_crypt-14.0.0.dist-info/RECORD
