Metadata-Version: 2.1
Name: cover_crypt
Version: 14.0.0
Classifier: Programming Language :: Rust
Classifier: Programming Language :: Python :: Implementation :: CPython
Classifier: Programming Language :: Python :: Implementation :: PyPy
Requires-Dist: cffi
License-File: LICENSE.md
Summary: Cosmian Cloudproof Covercrypt library
Author: Théophile Brézot<theophile.brezot@cosmian.com>
Author-email: Théophile Brézot<theophile.brezot@cosmian.com>
Requires-Python: >=3.7
Project-URL: Source Code, https://github.com/cosmian/cloudproof_rust/
